pandas_dataclasses/__init__.py
pandas_dataclasses/py.typed
pandas_dataclasses/core/__init__.py
pandas_dataclasses/core/api.py
pandas_dataclasses/core/specs.py
pandas_dataclasses/core/tagging.py
pandas_dataclasses/core/typing.py
pandas_dataclasses/extras/__init__.py
pandas_dataclasses/extras/hints.py
pandas_dataclasses/extras/new.py
pandas_dataclasses-1.0.0.dist-info/METADATA
pandas_dataclasses-1.0.0.dist-info/WHEEL
pandas_dataclasses-1.0.0.dist-info/licenses/LICENSE
pandas_dataclasses-1.0.0.dist-info/RECORD
