Metadata-Version: 2.4
Name: pandas-dataclasses
Version: 1.0.0
Summary: pandas data creation by data classes
Project-URL: homepage, https://astropenguin.github.io/pandas-dataclasses/v1.0.0
Project-URL: repository, https://github.com/astropenguin/pandas-dataclasses
Author-email: Akio Taniguchi <taniguchi.akio@gmail.com>
License: MIT License
License-File: LICENSE
Keywords: dataclasses,pandas,specifications,typing
Classifier: License :: OSI Approved :: MIT License
Classifier: Programming Language :: Python :: 3
Classifier: Programming Language :: Python :: 3.9
Classifier: Programming Language :: Python :: 3.10
Classifier: Programming Language :: Python :: 3.11
Classifier: Programming Language :: Python :: 3.12
Classifier: Programming Language :: Python :: 3.13
Requires-Python: <3.14,>=3.9
Requires-Dist: numpy<3.0,>=1.22
Requires-Dist: pandas-stubs<3.0,>=1.5
Requires-Dist: pandas<3.0,>=1.5
Requires-Dist: typing-extensions<5.0,>=4.1
